MANIFEST.in
README.md
setup.py
tilde/__init__.py
tilde.egg-info/PKG-INFO
tilde.egg-info/SOURCES.txt
tilde.egg-info/dependency_links.txt
tilde.egg-info/requires.txt
tilde.egg-info/top_level.txt
tilde/apps/__init__.py
tilde/apps/atomic_relaxation/__init__.py
tilde/apps/atomic_relaxation/atomic_relaxation.py
tilde/apps/atomic_relaxation/manifest.json
tilde/apps/example_app/__init__.py
tilde/apps/example_app/example_app.py
tilde/apps/example_app/manifest.json
tilde/apps/perovskite_tilting/__init__.py
tilde/apps/perovskite_tilting/manifest.json
tilde/apps/perovskite_tilting/perovskite_tilting.py
tilde/berlinium/__init__.py
tilde/berlinium/async_impl.py
tilde/berlinium/block_impl.py
tilde/berlinium/categs.py
tilde/berlinium/cubicspline.py
tilde/berlinium/dos.py
tilde/berlinium/impl.py
tilde/berlinium/plotter.py
tilde/berlinium/redirect.py
tilde/classifiers/__init__.py
tilde/classifiers/basisset.py
tilde/classifiers/defects.py
tilde/classifiers/dimensions.py
tilde/classifiers/example.py
tilde/classifiers/isolated.py
tilde/classifiers/organics.py
tilde/classifiers/perovskites.py
tilde/classifiers/surfaces.py
tilde/classifiers/xc_treatment.py
tilde/connectors/__init__.py
tilde/connectors/local.py
tilde/core/__init__.py
tilde/core/api.py
tilde/core/common.py
tilde/core/constants.py
tilde/core/electron_structure.py
tilde/core/libxc_functionals.py
tilde/core/model.py
tilde/core/orm_tools.py
tilde/core/settings.py
tilde/core/symmetry.py
tilde/data/sql/init-data.sql
tilde/parsers/__init__.py
tilde/parsers/CRYSTAL/CRYSTAL.py
tilde/parsers/CRYSTAL/__init__.py
tilde/parsers/CRYSTAL/manifest.json
tilde/parsers/QuantumESPRESSO/QuantumESPRESSO.py
tilde/parsers/QuantumESPRESSO/__init__.py
tilde/parsers/QuantumESPRESSO/manifest.json
tilde/parsers/VASP/VASP.py
tilde/parsers/VASP/__init__.py
tilde/parsers/VASP/manifest.json
utils/chk_tilde_install.py
utils/entry.py
utils/gui_server.py
utils/tilde